[
    {
        "PosterName": "Abdulla",
        "PosterTitle": "Hej Bloggen",
        "PosterComment": "Tjennaaa\nJag skulle vilja testa det h\u00E4r...\nUndrar om allt kommer fungera hihi\nOkej, hejd\u00E5 bloggen!!!",
        "DateOfPost": "2021-01-12T20:58:32.4368601+01:00"
    },
    {
        "PosterName": "Peter",
        "PosterTitle": "J\u00E4vla tjat",
        "PosterComment": "J\u00E4vla mycket tjat om krav hit o krav dit.",
        "DateOfPost": "2021-01-12T20:58:51.6411339+01:00"
    },
    {
        "PosterName": "Harald",
        "PosterTitle": "\u00D6l",
        "PosterComment": "\u00D6l \u00E4r fan g\u00F6tt\nYEEAHHHHHHHHHHHHH\nBOIIII",
        "DateOfPost": "2021-01-12T20:59:09.2681334+01:00"
    }
]